fistro/__init__.py
fistro/config.py
fistro/exceptions.py
fistro/factory.py
fistro/fistro.py
fistro/generators.py
fistro/utils.py
fistro-0.3.0.dist-info/LICENSE
fistro-0.3.0.dist-info/WHEEL
fistro-0.3.0.dist-info/METADATA
fistro-0.3.0.dist-info/RECORD
