Metadata-Version: 2.1
Name: fistro
Version: 0.3.0
Summary: A fixture generator based on type annotations.
Home-page: https://github.com/headsrooms/fistro
License: MIT
Keywords: fixture,testing,tool,dataclasses,annotations
Author: Pablo Cabezas
Author-email: headsrooms@gmail.com
Requires-Python: >=3.10,<4.0
Classifier: License :: OSI Approved :: MIT License
Classifier: Programming Language :: Python :: 3
Classifier: Programming Language :: Python :: 3.10
Project-URL: Repository, https://github.com/headsrooms/fistro
